netbox_gateways/__init__.py
netbox_gateways/filtersets.py
netbox_gateways/forms.py
netbox_gateways/models.py
netbox_gateways/navigation.py
netbox_gateways/tables.py
netbox_gateways/template_content.py
netbox_gateways/urls.py
netbox_gateways/views.py
netbox_gateways/api/__init__.py
netbox_gateways/api/serializers.py
netbox_gateways/api/urls.py
netbox_gateways/api/views.py
netbox_gateways/graphql/__init__.py
netbox_gateways/graphql/filters.py
netbox_gateways/graphql/schema.py
netbox_gateways/graphql/types.py
netbox_gateways/migrations/0001_netbox_gateways.py
netbox_gateways/migrations/0002_custom_fields.py
netbox_gateways/migrations/0003_owner.py
netbox_gateways/migrations/__init__.py
netbox_gateways/templates/netbox_gateways/gateway.html
netbox_gateways/templates/netbox_gateways/ip_card.html
netbox_gateways/templates/netbox_gateways/prefix_card.html
netbox_gateways-0.9.2.dist-info/METADATA
netbox_gateways-0.9.2.dist-info/WHEEL
netbox_gateways-0.9.2.dist-info/top_level.txt
netbox_gateways-0.9.2.dist-info/RECORD
