Metadata-Version: 2.4
Name: netbox-gateways
Version: 0.9.2
Summary: Manage simple prefix default gateways
Dynamic: description
Dynamic: description-content-type
Dynamic: summary
